{"primaryContentSections":[{"kind":"content","content":[{"anchor":"Summary","level":2,"type":"heading","text":"Summary"},{"type":"paragraph","inlineContent":[{"type":"text","text":"The old Ticketmaster "},{"type":"strong","inlineContent":[{"type":"text","text":"Presence SDK"}]},{"type":"text","text":" framework has been replaced by two new frameworks:"}]},{"type":"unorderedList","items":[{"content":[{"type":"paragraph","inlineContent":[{"type":"strong","inlineContent":[{"type":"text","text":"Tickets"}]},{"type":"text","text":": Post-Purchase functionality such as viewing purchased Events, Tickets, and Barcodes"}]}]},{"content":[{"type":"paragraph","inlineContent":[{"type":"strong","inlineContent":[{"type":"text","text":"Authentication"}]},{"type":"text","text":": Authentication functionality such as Login, Logout, Refresh Tokens, and Member Info"}]}]}]},{"type":"paragraph","inlineContent":[{"type":"text","text":"Below is a list of class and method name mapping between the old Presence 1.X or 2.X and the new Authentication 1.X and Tickets 3.X."}]},{"anchor":"Properties","level":2,"type":"heading","text":"Properties"},{"rows":[[[{"type":"paragraph","inlineContent":[{"type":"text","text":"Presence framework"}]}],[{"type":"paragraph","inlineContent":[{"type":"text","text":"Tickets\/Authentication frameworks"}]}]],[[{"type":"paragraph","inlineContent":[{"type":"text","text":"PSDK."},{"type":"strong","inlineContent":[{"type":"text","text":"shared"}]}]}],[{"type":"paragraph","inlineContent":[{"type":"strong","inlineContent":[{"type":"text","text":"TMTickets.shared"}]}]}]],[[{"type":"paragraph","inlineContent":[{"type":"text","text":"PSDK.shared."},{"type":"strong","inlineContent":[{"type":"text","text":"version"}]}]}],[{"type":"paragraph","inlineContent":[{"type":"text","text":"TMTickets.shared."},{"type":"strong","inlineContent":[{"type":"text","text":"version"}]}]}]],[[{"type":"paragraph","inlineContent":[{"type":"text","text":"PSDK.shared."},{"type":"strong","inlineContent":[{"type":"text","text":"orderDelegate"}]}]}],[{"type":"paragraph","inlineContent":[{"type":"text","text":"TMTickets.shared."},{"type":"strong","inlineContent":[{"type":"text","text":"orderDelegate"}]}]}]],[[{"type":"paragraph","inlineContent":[{"type":"text","text":"PSDK.shared."},{"type":"strong","inlineContent":[{"type":"text","text":"moduleDelegate"}]}]}],[{"type":"paragraph","inlineContent":[{"type":"text","text":"TMTickets.shared."},{"type":"strong","inlineContent":[{"type":"text","text":"moduleDelegate"}]}]}]],[[{"type":"paragraph","inlineContent":[{"type":"text","text":"PSDK.shared."},{"type":"strong","inlineContent":[{"type":"text","text":"loginDelegate"}]}]}],[{"type":"paragraph","inlineContent":[{"type":"strong","inlineContent":[{"type":"text","text":"TMAuthentication.shared.delegate"}]}]}]],[[{"type":"paragraph","inlineContent":[{"type":"strong","inlineContent":[{"type":"text","text":"PresenceEventAnalytics"}]},{"type":"text","text":" notifications"}]}],[{"type":"paragraph","inlineContent":[{"type":"text","text":"TMTickets.shared."},{"type":"strong","inlineContent":[{"type":"text","text":"analyticsDelegate"}]}]}]]],"type":"table","alignments":["left","left"],"header":"row"},{"anchor":"Configuration","level":2,"type":"heading","text":"Configuration"},{"type":"table","rows":[[[{"type":"paragraph","inlineContent":[{"type":"text","text":"Presence framework"}]}],[{"type":"paragraph","inlineContent":[{"type":"text","text":"Tickets\/Authentication frameworks"}]}]],[[{"type":"paragraph","inlineContent":[{"type":"text","text":"PSDK.shared."},{"type":"strong","inlineContent":[{"type":"text","text":"setConfig"}]},{"type":"text","text":"(consumerKey: …)"}]}],[{"type":"paragraph","inlineContent":[{"type":"text","text":"TMAuthentication.shared."},{"type":"strong","inlineContent":[{"type":"text","text":"configure"}]},{"type":"text","text":"(apiKey: …) and TMTickets.shared**.configure**(success:failure)"}]}]],[[{"type":"paragraph","inlineContent":[{"type":"text","text":"PSDK.shared."},{"type":"strong","inlineContent":[{"type":"text","text":"checkConfig"}]},{"type":"text","text":"(success:failure:)"}]}],[{"type":"paragraph","inlineContent":[{"type":"text","text":"not needed anymore, as success\/error blocks are now part of: TMTickets.shared."},{"type":"strong","inlineContent":[{"type":"text","text":"configure"}]},{"type":"text","text":"("},{"type":"strong","inlineContent":[{"type":"text","text":"success"}]},{"type":"text","text":":"},{"type":"strong","inlineContent":[{"type":"text","text":"failure"}]},{"type":"text","text":")"}]}]],[[{"type":"paragraph","inlineContent":[{"type":"text","text":"PSDK.shared."},{"type":"strong","inlineContent":[{"type":"text","text":"start"}]},{"type":"text","text":"(presenceView:)"}]}],[{"type":"paragraph","inlineContent":[{"type":"text","text":"TMTickets.shared."},{"type":"strong","inlineContent":[{"type":"text","text":"start"}]},{"type":"text","text":"(ticketsView:)"}]}]]],"header":"row"},{"anchor":"Authentication","level":2,"type":"heading","text":"Authentication"},{"type":"paragraph","inlineContent":[{"type":"text","text":"Note that all Authentication related methods have been moved to "},{"type":"strong","inlineContent":[{"type":"text","text":"TMAuthentication.shared"}]},{"type":"text","text":"."}]},{"type":"table","rows":[[[{"type":"paragraph","inlineContent":[{"type":"text","text":"Presence framework"}]}],[{"type":"paragraph","inlineContent":[{"type":"text","text":"Authentication framework"}]}]],[[{"type":"paragraph","inlineContent":[{"type":"text","text":"PSDK.shared."},{"type":"strong","inlineContent":[{"type":"text","text":"loginDelegate"}]}]}],[{"type":"paragraph","inlineContent":[{"type":"strong","inlineContent":[{"type":"text","text":"TMAuthentication.shared.delegate"}]}]}]],[[{"type":"paragraph","inlineContent":[{"type":"text","text":"PSDK.shared."},{"type":"strong","inlineContent":[{"type":"text","text":"login"}]},{"type":"text","text":"(…)"}]}],[{"type":"paragraph","inlineContent":[{"type":"text","text":"TMAuthentication.shared."},{"type":"strong","inlineContent":[{"type":"text","text":"login"}]},{"type":"text","text":"(…)"}]}]],[[{"type":"paragraph","inlineContent":[{"type":"text","text":"PSDK.shared."},{"type":"strong","inlineContent":[{"type":"text","text":"hostLoginQueryParams"}]}]}],[{"type":"paragraph","inlineContent":[{"type":"text","text":"TMAuthentication.shared.login(backend: ."},{"type":"strong","inlineContent":[{"type":"text","text":"HostModernAccounts"}]},{"type":"text","text":", "},{"type":"strong","inlineContent":[{"type":"text","text":"loginProperties"}]},{"type":"text","text":": …)"}]}]],[[{"type":"paragraph","inlineContent":[{"type":"text","text":"PSDK.shared."},{"type":"strong","inlineContent":[{"type":"text","text":"archticsLoginQueryParams"}]}]}],[{"type":"paragraph","inlineContent":[{"type":"text","text":"TMAuthentication.shared.login(backend: ."},{"type":"strong","inlineContent":[{"type":"text","text":"TeamModernAccounts"}]},{"type":"text","text":", "},{"type":"strong","inlineContent":[{"type":"text","text":"loginProperties"}]},{"type":"text","text":": …)"}]}]],[[{"type":"paragraph","inlineContent":[{"type":"text","text":"PSDK.shared."},{"type":"strong","inlineContent":[{"type":"text","text":"sportXRLoginQueryParams"}]}]}],[{"type":"paragraph","inlineContent":[{"type":"text","text":"TMAuthentication.shared.login(backend: ."},{"type":"strong","inlineContent":[{"type":"text","text":"SportXR"}]},{"type":"text","text":", "},{"type":"strong","inlineContent":[{"type":"text","text":"loginProperties"}]},{"type":"text","text":": …)"}]}]],[[{"type":"paragraph","inlineContent":[{"type":"text","text":"PSDK.shared."},{"type":"strong","inlineContent":[{"type":"text","text":"isLoggedIn"}]},{"type":"text","text":"()"}]}],[{"type":"paragraph","inlineContent":[{"type":"text","text":"TMAuthentication.shared."},{"type":"strong","inlineContent":[{"type":"text","text":"hasUnexpiredToken"}]},{"type":"text","text":"()"}]}]],[[{"type":"paragraph","inlineContent":[{"type":"text","text":"PSDK.shared."},{"type":"strong","inlineContent":[{"type":"text","text":"isLoggedIntoHost"}]},{"type":"text","text":"()"}]}],[{"type":"paragraph","inlineContent":[{"type":"text","text":"TMAuthentication.shared."},{"type":"strong","inlineContent":[{"type":"text","text":"hasUnexpiredToken"}]},{"type":"text","text":"(backend: ."},{"type":"strong","inlineContent":[{"type":"text","text":"HostModernAccounts"}]},{"type":"text","text":")"}]}]],[[{"type":"paragraph","inlineContent":[{"type":"text","text":"PSDK.shared."},{"type":"strong","inlineContent":[{"type":"text","text":"isLoggedIntoTeam"}]},{"type":"text","text":"()"}]}],[{"type":"paragraph","inlineContent":[{"type":"text","text":"TMAuthentication.shared."},{"type":"strong","inlineContent":[{"type":"text","text":"hasUnexpiredToken"}]},{"type":"text","text":"(backend: ."},{"type":"strong","inlineContent":[{"type":"text","text":"TeamModernAccounts"}]},{"type":"text","text":")"}]}]],[[{"type":"paragraph","inlineContent":[{"type":"text","text":"PSDK.shared."},{"type":"strong","inlineContent":[{"type":"text","text":"isLoggedIntoSportXR"}]},{"type":"text","text":"()"}]}],[{"type":"paragraph","inlineContent":[{"type":"text","text":"TMAuthentication.shared."},{"type":"strong","inlineContent":[{"type":"text","text":"hasUnexpiredToken"}]},{"type":"text","text":"(backend: ."},{"type":"strong","inlineContent":[{"type":"text","text":"SportXR"}]},{"type":"text","text":")"}]}]],[[{"type":"paragraph","inlineContent":[{"type":"text","text":"PSDK.shared."},{"type":"strong","inlineContent":[{"type":"text","text":"hasUserSignedIn"}]},{"type":"text","text":"()"}]}],[{"type":"paragraph","inlineContent":[{"type":"text","text":"TMAuthentication.shared."},{"type":"strong","inlineContent":[{"type":"text","text":"hasToken"}]},{"type":"text","text":"()"}]}]],[[{"type":"paragraph","inlineContent":[{"type":"text","text":"PSDK.shared."},{"type":"strong","inlineContent":[{"type":"text","text":"hasUserSignedInHost"}]},{"type":"text","text":"()"}]}],[{"type":"paragraph","inlineContent":[{"type":"text","text":"TMAuthentication.shared."},{"type":"strong","inlineContent":[{"type":"text","text":"hasToken"}]},{"type":"text","text":"(backend: ."},{"type":"strong","inlineContent":[{"type":"text","text":"HostModernAccounts"}]},{"type":"text","text":")"}]}]],[[{"type":"paragraph","inlineContent":[{"type":"text","text":"PSDK.shared."},{"type":"strong","inlineContent":[{"type":"text","text":"hasUserSignedInTeam"}]},{"type":"text","text":"()"}]}],[{"type":"paragraph","inlineContent":[{"type":"text","text":"TMAuthentication.shared."},{"type":"strong","inlineContent":[{"type":"text","text":"hasToken"}]},{"type":"text","text":"(backend: ."},{"type":"strong","inlineContent":[{"type":"text","text":"TeamModernAccounts"}]},{"type":"text","text":")"}]}]],[[{"type":"paragraph","inlineContent":[{"type":"text","text":"PSDK.shared."},{"type":"strong","inlineContent":[{"type":"text","text":"hasUserSignedInSportXR"}]},{"type":"text","text":"()"}]}],[{"type":"paragraph","inlineContent":[{"type":"text","text":"TMAuthentication.shared."},{"type":"strong","inlineContent":[{"type":"text","text":"hasToken"}]},{"type":"text","text":"(backend: ."},{"type":"strong","inlineContent":[{"type":"text","text":"SportXR"}]},{"type":"text","text":")"}]}]],[[{"type":"paragraph","inlineContent":[{"type":"text","text":"PSDK.shared."},{"type":"strong","inlineContent":[{"type":"text","text":"getAccessToken"}]},{"type":"text","text":"(…)"}]}],[{"type":"paragraph","inlineContent":[{"type":"text","text":"TMAuthentication.shared."},{"type":"strong","inlineContent":[{"type":"text","text":"validToken"}]},{"type":"text","text":"(…)"}]}]],[[{"type":"paragraph","inlineContent":[{"type":"text","text":"PSDK.shared."},{"type":"strong","inlineContent":[{"type":"text","text":"getMemberInfo"}]},{"type":"text","text":"(…)"}]}],[{"type":"paragraph","inlineContent":[{"type":"text","text":"TMAuthentication.shared."},{"type":"strong","inlineContent":[{"type":"text","text":"memberInfo"}]},{"type":"text","text":"(…)"}]}]],[[{"type":"paragraph","inlineContent":[{"type":"text","text":"PSDK.shared."},{"type":"strong","inlineContent":[{"type":"text","text":"startMFAValidation"}]},{"type":"text","text":"(…)"}]}],[{"type":"paragraph","inlineContent":[{"type":"text","text":"TMAuthentication.shared."},{"type":"strong","inlineContent":[{"type":"text","text":"validateMFAToken"}]},{"type":"text","text":"(…)"}]}]],[[{"type":"paragraph","inlineContent":[{"type":"text","text":"PSDK.shared."},{"type":"strong","inlineContent":[{"type":"text","text":"logout"}]},{"type":"text","text":"(…)"}]}],[{"type":"paragraph","inlineContent":[{"type":"text","text":"TMAuthentication.shared."},{"type":"strong","inlineContent":[{"type":"text","text":"logout"}]},{"type":"text","text":"(backend: "},{"type":"strong","inlineContent":[{"type":"text","text":"nil"}]},{"type":"text","text":", …)"}]}]],[[{"type":"paragraph","inlineContent":[{"type":"text","text":"PSDK.shared."},{"type":"strong","inlineContent":[{"type":"text","text":"logOutHost"}]},{"type":"text","text":"(…)"}]}],[{"type":"paragraph","inlineContent":[{"type":"text","text":"TMAuthentication.shared."},{"type":"strong","inlineContent":[{"type":"text","text":"logout"}]},{"type":"text","text":"(backend: ."},{"type":"strong","inlineContent":[{"type":"text","text":"HostModernAccounts"}]},{"type":"text","text":", …)"}]}]],[[{"type":"paragraph","inlineContent":[{"type":"text","text":"PSDK.shared."},{"type":"strong","inlineContent":[{"type":"text","text":"logOutTeam"}]},{"type":"text","text":"(…)"}]}],[{"type":"paragraph","inlineContent":[{"type":"text","text":"TMAuthentication.shared."},{"type":"strong","inlineContent":[{"type":"text","text":"logout"}]},{"type":"text","text":"(backend: ."},{"type":"strong","inlineContent":[{"type":"text","text":"TeamModernAccounts"}]},{"type":"text","text":", …)"}]}]],[[{"type":"paragraph","inlineContent":[{"type":"text","text":"PSDK.shared."},{"type":"strong","inlineContent":[{"type":"text","text":"logOutSportXR"}]},{"type":"text","text":"(…)"}]}],[{"type":"paragraph","inlineContent":[{"type":"text","text":"TMAuthentication.shared."},{"type":"strong","inlineContent":[{"type":"text","text":"logout"}]},{"type":"text","text":"(backend: ."},{"type":"strong","inlineContent":[{"type":"text","text":"SportXR"}]},{"type":"text","text":", …)"}]}]],[[{"type":"paragraph","inlineContent":[{"type":"strong","inlineContent":[{"type":"text","text":"PresenceOAuthProvider"}]}]}],[{"type":"paragraph","inlineContent":[{"type":"strong","inlineContent":[{"type":"text","text":"TMAuthenticationProvider"}]}]}]]],"header":"row"},{"anchor":"Operations","level":2,"type":"heading","text":"Operations"},{"type":"table","rows":[[[{"type":"paragraph","inlineContent":[{"type":"text","text":"Presence framework"}]}],[{"type":"paragraph","inlineContent":[{"type":"text","text":"Tickets framework"}]}]],[[{"type":"paragraph","inlineContent":[{"type":"text","text":"PSDK.shared."},{"type":"strong","inlineContent":[{"type":"text","text":"jumpToOrderOrEvent"}]},{"type":"text","text":"(id:type:action:)"}]}],[{"type":"paragraph","inlineContent":[{"type":"text","text":"TMTickets.shared."},{"type":"strong","inlineContent":[{"type":"text","text":"display"}]},{"type":"text","text":"(orderOrEventId:type:action:)"}]}]],[[{"type":"paragraph","inlineContent":[{"type":"text","text":"PSDK.shared."},{"type":"strong","inlineContent":[{"type":"text","text":"setTicketsActionButton"}]},{"type":"text","text":"(title: “foo”)"}]}],[{"type":"paragraph","inlineContent":[{"type":"text","text":"TMTickets.shared."},{"type":"strong","inlineContent":[{"type":"text","text":"ticketsNavBarButtonText"}]},{"type":"text","text":" = “foo”"}]}]],[[{"type":"paragraph","inlineContent":[{"type":"text","text":"PSDK.shared."},{"type":"strong","inlineContent":[{"type":"text","text":"getTicketsActionBarButtonText"}]},{"type":"text","text":"()"}]}],[{"type":"paragraph","inlineContent":[{"type":"text","text":"let text = TMTickets.shared."},{"type":"strong","inlineContent":[{"type":"text","text":"ticketsNavBarButtonText"}]}]}]],[[{"type":"paragraph","inlineContent":[{"type":"text","text":"PSDK.shared."},{"type":"strong","inlineContent":[{"type":"text","text":"setUserTracking"}]},{"type":"text","text":"(enabled: false)"}]}],[{"type":"paragraph","inlineContent":[{"type":"text","text":"TMTickets.shared."},{"type":"strong","inlineContent":[{"type":"text","text":"userTrackingEnabled"}]},{"type":"text","text":" = false"}]}]]],"header":"row"},{"anchor":"Branding","level":2,"type":"heading","text":"Branding"},{"type":"paragraph","inlineContent":[{"type":"text","text":"By default Tickets inherits basic branding from Authentication via "},{"type":"strong","inlineContent":[{"type":"text","text":"TMAuthentication.Branding"}]},{"type":"text","text":" passed into TMAuthentication.shared."},{"type":"strong","inlineContent":[{"type":"text","text":"configure"}]},{"type":"text","text":"("},{"type":"strong","inlineContent":[{"type":"text","text":"brandedServiceSettings"}]},{"type":"text","text":":success:failure)."}]},{"type":"paragraph","inlineContent":[{"type":"text","text":"So the following methods are optional unless you need to customize Tickets branding beyond the basic branding provided by Authentication."}]},{"type":"table","rows":[[[{"type":"paragraph","inlineContent":[{"type":"text","text":"Presence framework"}]}],[{"type":"paragraph","inlineContent":[{"type":"text","text":"Tickets framework"}]}]],[[{"type":"paragraph","inlineContent":[{"type":"text","text":"PSDK.shared."},{"type":"strong","inlineContent":[{"type":"text","text":"setBrandingColors"}]},{"type":"text","text":"(…)"}]}],[{"type":"paragraph","inlineContent":[{"type":"text","text":"TMTickets.shared."},{"type":"strong","inlineContent":[{"type":"text","text":"brandingColorsOverride"}]},{"type":"text","text":" = TMTickets.BrandingColors()"}]}]],[[{"type":"paragraph","inlineContent":[{"type":"text","text":"PSDK.shared."},{"type":"strong","inlineContent":[{"type":"text","text":"enableTMBrandingColorOverride"}]},{"type":"text","text":"()"}]}],[{"type":"paragraph","inlineContent":[{"type":"text","text":"TMTickets.shared."},{"type":"strong","inlineContent":[{"type":"text","text":"brandingColorButtonOverride"}]},{"type":"text","text":" = true"}]}]],[[{"type":"paragraph","inlineContent":[{"type":"text","text":"PSDK.shared."},{"type":"strong","inlineContent":[{"type":"text","text":"doNotBrandNavBar"}]},{"type":"text","text":"()"}]}],[{"type":"paragraph","inlineContent":[{"type":"text","text":"TMTickets.shared."},{"type":"strong","inlineContent":[{"type":"text","text":"brandingColorNavBarOverride"}]},{"type":"text","text":" = true"}]}]],[[{"type":"paragraph","inlineContent":[{"type":"text","text":"PSDK.shared."},{"type":"strong","inlineContent":[{"type":"text","text":"setLogo"}]},{"type":"text","text":"(…)"}]}],[{"type":"paragraph","inlineContent":[{"type":"text","text":"TMTickets.shared."},{"type":"strong","inlineContent":[{"type":"text","text":"brandingTeamLogoImage"}]},{"type":"text","text":" = UIImage()"}]}]],[[{"type":"paragraph","inlineContent":[{"type":"text","text":"PSDK.shared."},{"type":"strong","inlineContent":[{"type":"text","text":"setTheme"}]},{"type":"text","text":"(theme:)"}]}],[{"type":"paragraph","inlineContent":[{"type":"text","text":"theme is now part of "},{"type":"strong","inlineContent":[{"type":"text","text":"TMAuthentication.Branding"}]},{"type":"text","text":" and "},{"type":"strong","inlineContent":[{"type":"text","text":"TMTickets.BrandingColors"}]}]}]]],"header":"row"},{"anchor":"Custom-Modules","level":2,"type":"heading","text":"Custom Modules"},{"type":"table","rows":[[[{"type":"paragraph","inlineContent":[{"type":"text","text":"Presence framework"}]}],[{"type":"paragraph","inlineContent":[{"type":"text","text":"Tickets framework"}]}]],[[{"type":"paragraph","inlineContent":[{"type":"text","text":"PSDK.shared."},{"type":"strong","inlineContent":[{"type":"text","text":"moduleDelegate"}]}]}],[{"type":"paragraph","inlineContent":[{"type":"text","text":"TMTickets.shared."},{"type":"strong","inlineContent":[{"type":"text","text":"moduleDelegate"}]}]}]],[[{"type":"paragraph","inlineContent":[{"type":"strong","inlineContent":[{"type":"text","text":"PresenceModuleDelegate"}]}]}],[{"type":"paragraph","inlineContent":[{"type":"strong","inlineContent":[{"type":"text","text":"TMTicketsModuleDelegate"}]}]}]],[[{"type":"paragraph","inlineContent":[{"type":"text","text":"- "},{"type":"strong","inlineContent":[{"type":"text","text":"addCustomModules"}]},{"type":"text","text":"(eventOrders:completion:)"}]}],[{"type":"paragraph","inlineContent":[{"type":"text","text":"- "},{"type":"strong","inlineContent":[{"type":"text","text":"addCustomModule"}]},{"type":"text","text":"s(event:completion:)"}]}]],[[{"type":"paragraph","inlineContent":[{"type":"text","text":"- "},{"type":"strong","inlineContent":[{"type":"text","text":"handleModuleActionButton"}]},{"type":"text","text":"(moduleIdentifier:buttonTitle: callbackValue:eventOrders:completion:)"}]}],[{"type":"paragraph","inlineContent":[{"type":"text","text":"- "},{"type":"strong","inlineContent":[{"type":"text","text":"handleModuleActionButton"}]},{"type":"text","text":"(event:module:button: completion:)"}]}]],[[{"type":"paragraph","inlineContent":[{"type":"text","text":"- "},{"type":"strong","inlineContent":[{"type":"text","text":"userDidPressActionButton"}]},{"type":"text","text":"(moduleIdentifier:buttonTitle: callbackValue:eventOrders:)"}]}],[{"type":"paragraph","inlineContent":[{"type":"strong","inlineContent":[{"type":"text","text":"TMTicketsAnalyticsDelegate"}]},{"type":"text","text":".userDidPerform(action: ."},{"type":"strong","inlineContent":[{"type":"text","text":"moduleActionButton"}]},{"type":"text","text":", metadata:)"}]}]],[[{"type":"paragraph","inlineContent":[{"type":"strong","inlineContent":[{"type":"text","text":"PSDKTicketsModule"}]}]}],[{"type":"paragraph","inlineContent":[{"type":"strong","inlineContent":[{"type":"text","text":"TMTicketsModule"}]}]}]],[[{"type":"paragraph","inlineContent":[{"type":"strong","inlineContent":[{"type":"text","text":"PresenceModuleHeaderView"}]}]}],[{"type":"paragraph","inlineContent":[{"type":"strong","inlineContent":[{"type":"text","text":"TMTicketsModuleHeaderView"}]}]}]],[[{"type":"paragraph","inlineContent":[{"type":"text","text":"PSDKTicketsModule."},{"type":"strong","inlineContent":[{"type":"text","text":"accountManagerSeatUpgrades"}]},{"type":"text","text":"(…)"}]}],[{"type":"paragraph","inlineContent":[{"type":"text","text":"TMTicketsPrebuiltModule. "},{"type":"strong","inlineContent":[{"type":"text","text":"accountManagerSeatUpgrades"}]},{"type":"text","text":"(…)"}]}]],[[{"type":"paragraph","inlineContent":[{"type":"text","text":"PSDKTicketsModule."},{"type":"strong","inlineContent":[{"type":"text","text":"accountManagerMoreTicketActions"}]},{"type":"text","text":"(…)"}]}],[{"type":"paragraph","inlineContent":[{"type":"text","text":"TMTicketsPrebuiltModule. "},{"type":"strong","inlineContent":[{"type":"text","text":"accountManagerMoreTicketActions"}]},{"type":"text","text":"(…)"}]}]],[[{"type":"paragraph","inlineContent":[{"type":"text","text":"PSDKTicketsModule."},{"type":"strong","inlineContent":[{"type":"text","text":"venueDirectionsViaAppleMaps"}]},{"type":"text","text":"(…)"}]}],[{"type":"paragraph","inlineContent":[{"type":"text","text":"TMTicketsPrebuiltModule. "},{"type":"strong","inlineContent":[{"type":"text","text":"venueDirectionsViaAppleMaps"}]},{"type":"text","text":"(…)"}]}]],[[{"type":"paragraph","inlineContent":[{"type":"text","text":"PSDKTicketsModule."},{"type":"strong","inlineContent":[{"type":"text","text":"venueConcessions"}]},{"type":"text","text":"(…)"}]}],[{"type":"paragraph","inlineContent":[{"type":"text","text":"TMTicketsPrebuiltModule."},{"type":"strong","inlineContent":[{"type":"text","text":"venueConcessions"}]},{"type":"text","text":"(…)"}]}]]],"header":"row"},{"anchor":"Order-Delegate","level":2,"type":"heading","text":"Order Delegate"},{"type":"paragraph","inlineContent":[{"type":"text","text":"All User-behavior analytics have been moved to "},{"type":"strong","inlineContent":[{"type":"text","text":"TMTicketsAnalyticsDelegate"}]},{"type":"text","text":"."}]},{"type":"paragraph","inlineContent":[{"type":"text","text":"The remaining methods in "},{"type":"strong","inlineContent":[{"type":"text","text":"TMTicketsOrderDelegate"}]},{"type":"text","text":" represent either:"}]},{"type":"unorderedList","items":[{"content":[{"type":"paragraph","inlineContent":[{"type":"text","text":"non-analytics: actions that require your application to do something, such as handleNavBarButtonAction"}]}]},{"content":[{"type":"paragraph","inlineContent":[{"type":"text","text":"analytics that are not based on User-behavior: such as didUpdateEvents"}]}]}]},{"type":"table","rows":[[[{"type":"paragraph","inlineContent":[{"type":"text","text":"Presence framework"}]}],[{"type":"paragraph","inlineContent":[{"type":"text","text":"Tickets framework"}]}]],[[{"type":"paragraph","inlineContent":[{"type":"text","text":"PSDK.shared."},{"type":"strong","inlineContent":[{"type":"text","text":"orderDelegate"}]}]}],[{"type":"paragraph","inlineContent":[{"type":"text","text":"TMTickets.shared."},{"type":"strong","inlineContent":[{"type":"text","text":"orderDelegate"}]}]}]],[[{"type":"paragraph","inlineContent":[{"type":"strong","inlineContent":[{"type":"text","text":"PresenceOrderDelegate"}]}]}],[{"type":"paragraph","inlineContent":[{"type":"strong","inlineContent":[{"type":"text","text":"TMTicketsOrderDelegate"}]}]}]],[[{"type":"paragraph","inlineContent":[{"type":"text","text":"- "},{"type":"strong","inlineContent":[{"type":"text","text":"presentEventDetailsPage"}]},{"type":"text","text":"(…)"}]}],[{"type":"paragraph","inlineContent":[{"type":"emphasis","inlineContent":[{"type":"text","text":"no longer used"}]}]}]],[[{"type":"paragraph","inlineContent":[{"type":"text","text":"- "},{"type":"strong","inlineContent":[{"type":"text","text":"presentArtistDetailsPage"}]},{"type":"text","text":"(…)"}]}],[{"type":"paragraph","inlineContent":[{"type":"emphasis","inlineContent":[{"type":"text","text":"no longer used"}]}]}]],[[{"type":"paragraph","inlineContent":[{"type":"text","text":"- "},{"type":"strong","inlineContent":[{"type":"text","text":"presentVenueDetailsPage"}]},{"type":"text","text":"(…)"}]}],[{"type":"paragraph","inlineContent":[{"type":"emphasis","inlineContent":[{"type":"text","text":"no longer used"}]}]}]],[[{"type":"paragraph","inlineContent":[{"type":"text","text":"- "},{"type":"strong","inlineContent":[{"type":"text","text":"presentClientAppPage"}]},{"type":"text","text":"(…)"}]}],[{"type":"paragraph","inlineContent":[{"type":"text","text":"- "},{"type":"strong","inlineContent":[{"type":"text","text":"presentClientAppPage"}]},{"type":"text","text":"(…)"}]}]],[[{"type":"paragraph","inlineContent":[{"type":"text","text":"- "},{"type":"strong","inlineContent":[{"type":"text","text":"handleBarButtonAction"}]},{"type":"text","text":"(page: screenTitleName:eventOrders:)  and "},{"type":"strong","inlineContent":[{"type":"text","text":"handleBarButtonAction"}]},{"type":"text","text":"(page: buttonTitle:eventOrders:)"}]}],[{"type":"paragraph","inlineContent":[{"type":"text","text":"- "},{"type":"strong","inlineContent":[{"type":"text","text":"handleNavBarButtonAction"}]},{"type":"text","text":"(page: screenTitleName:event:)"}]}]],[[{"type":"paragraph","inlineContent":[{"type":"text","text":"- "},{"type":"strong","inlineContent":[{"type":"text","text":"didUpdateEvents"}]},{"type":"text","text":"(eventOrderArray:) and "},{"type":"strong","inlineContent":[{"type":"text","text":"didUpdateOrderedEvents"}]},{"type":"text","text":"()"}]}],[{"type":"paragraph","inlineContent":[{"type":"text","text":"- "},{"type":"strong","inlineContent":[{"type":"text","text":"didUpdateEvents"}]},{"type":"text","text":"(events:fromCache:)"}]}]],[[{"type":"paragraph","inlineContent":[{"type":"text","text":"- "},{"type":"strong","inlineContent":[{"type":"text","text":"didUpdateTickets"}]},{"type":"text","text":"(eventOrders:) and "},{"type":"strong","inlineContent":[{"type":"text","text":"didUpdateTickets"}]},{"type":"text","text":"(eventId:)"}]}],[{"type":"paragraph","inlineContent":[{"type":"text","text":"- "},{"type":"strong","inlineContent":[{"type":"text","text":"didUpdateTickets"}]},{"type":"text","text":"(event:fromCache)"}]}]],[[{"type":"paragraph","inlineContent":[{"type":"text","text":"- "},{"type":"strong","inlineContent":[{"type":"text","text":"didPresentEventList"}]},{"type":"text","text":"()"}]}],[{"type":"paragraph","inlineContent":[{"type":"strong","inlineContent":[{"type":"text","text":"TMTicketsAnalyticsDelegate"}]},{"type":"text","text":".userDidView(page: ."},{"type":"strong","inlineContent":[{"type":"text","text":"events"}]},{"type":"text","text":", metadata:)"}]}]],[[{"type":"paragraph","inlineContent":[{"type":"text","text":"- "},{"type":"strong","inlineContent":[{"type":"text","text":"didPresentTicketList"}]},{"type":"text","text":"()"}]}],[{"type":"paragraph","inlineContent":[{"type":"strong","inlineContent":[{"type":"text","text":"TMTicketsAnalyticsDelegate"}]},{"type":"text","text":".userDidView(page: ."},{"type":"strong","inlineContent":[{"type":"text","text":"eventTickets"}]},{"type":"text","text":", metadata:)"}]}]]],"header":"row"},{"anchor":"Analytics-Delegate","level":2,"type":"heading","text":"Analytics Delegate"},{"type":"paragraph","inlineContent":[{"type":"text","text":"Old notification-based "},{"type":"strong","inlineContent":[{"type":"text","text":"PresenceEventAnalytics"}]},{"type":"text","text":" have been replaced with a simplier "},{"type":"strong","inlineContent":[{"type":"text","text":"TMTicketsAnalyticsDelegate"}]},{"type":"text","text":"."}]},{"type":"table","rows":[[[{"type":"paragraph","inlineContent":[{"type":"text","text":"Presence framework"}]}],[{"type":"paragraph","inlineContent":[{"type":"text","text":"Tickets framework"}]}]],[[{"type":"paragraph","inlineContent":[{"type":"strong","inlineContent":[{"type":"text","text":"PresenceEventAnalytics"}]},{"type":"text","text":" notifications"}]}],[{"type":"paragraph","inlineContent":[{"type":"text","text":"TMTickets.shared."},{"type":"strong","inlineContent":[{"type":"text","text":"analyticsDelegate"}]}]}]],[[{"type":"paragraph","inlineContent":[{"type":"strong","inlineContent":[{"type":"text","text":"PresenceEventAnalytics"}]}]}],[{"type":"paragraph","inlineContent":[{"type":"strong","inlineContent":[{"type":"text","text":"TMTicketsAnalyticsDelegate"}]}]}]],[[{"type":"paragraph","inlineContent":[]}],[{"type":"paragraph","inlineContent":[{"type":"text","text":"- "},{"type":"strong","inlineContent":[{"type":"text","text":"userDidView"}]},{"type":"text","text":"(page:metadata:)"}]}]],[[{"type":"paragraph","inlineContent":[]}],[{"type":"paragraph","inlineContent":[{"type":"text","text":"- "},{"type":"strong","inlineContent":[{"type":"text","text":"userDidPerform"}]},{"type":"text","text":"(action:metadata:)"}]}]]],"header":"row"},{"anchor":"Login-Delegate","level":2,"type":"heading","text":"Login Delegate"},{"type":"paragraph","inlineContent":[{"type":"text","text":"Note that all Authentication related methods have been moved to "},{"type":"strong","inlineContent":[{"type":"text","text":"TMAuthentication.shared"}]},{"type":"text","text":"."}]},{"type":"paragraph","inlineContent":[{"type":"text","text":"The same Authentication-related information is available via:"}]},{"type":"unorderedList","items":[{"content":[{"type":"paragraph","inlineContent":[{"type":"text","text":"TMAuthentication.shared."},{"type":"strong","inlineContent":[{"type":"text","text":"delegate"}]}]}]},{"content":[{"type":"paragraph","inlineContent":[{"type":"text","text":"TMAuthentication.shared**.registerStateChanged**(block:)"}]}]},{"content":[{"type":"paragraph","inlineContent":[{"type":"text","text":"TMAuthentication."},{"type":"strong","inlineContent":[{"type":"text","text":"AuthNotification"}]}]}]}]},{"type":"paragraph","inlineContent":[{"type":"text","text":"For the purposes of comparison to the old "},{"type":"strong","inlineContent":[{"type":"text","text":"Presence"}]},{"type":"text","text":" framework, the "},{"type":"strong","inlineContent":[{"type":"text","text":"TMAuthenticationDelegate"}]},{"type":"text","text":" methods are listed below:"}]},{"type":"table","rows":[[[{"type":"paragraph","inlineContent":[{"type":"text","text":"Presence framework"}]}],[{"type":"paragraph","inlineContent":[{"type":"text","text":"Authentication framework"}]}]],[[{"type":"paragraph","inlineContent":[{"type":"text","text":"PSDK.shared."},{"type":"strong","inlineContent":[{"type":"text","text":"loginDelegate"}]}]}],[{"type":"paragraph","inlineContent":[{"type":"strong","inlineContent":[{"type":"text","text":"TMAuthentication.shared.delegate"}]}]}]],[[{"type":"paragraph","inlineContent":[{"type":"strong","inlineContent":[{"type":"text","text":"PresenceLoginDelegate"}]}]}],[{"type":"paragraph","inlineContent":[{"type":"strong","inlineContent":[{"type":"text","text":"TMAuthenticationDelegate"}]}]}]],[[{"type":"paragraph","inlineContent":[{"type":"text","text":"- "},{"type":"strong","inlineContent":[{"type":"text","text":"onLoginWindowDidDisplay"}]},{"type":"text","text":"(…)"}]}],[{"type":"paragraph","inlineContent":[{"type":"text","text":"- onStateChanged(backend:state: ."},{"type":"strong","inlineContent":[{"type":"text","text":"loginPresented"}]},{"type":"text","text":", error:)"}]}]],[[{"type":"paragraph","inlineContent":[{"type":"text","text":"- "},{"type":"strong","inlineContent":[{"type":"text","text":"onLoginForgotPasswordClicked"}]},{"type":"text","text":"(…)"}]}],[{"type":"paragraph","inlineContent":[{"type":"emphasis","inlineContent":[{"type":"text","text":"no longer used"}]}]}]],[[{"type":"paragraph","inlineContent":[{"type":"text","text":"- "},{"type":"strong","inlineContent":[{"type":"text","text":"onLoginMethodUsed"}]},{"type":"text","text":"(…)"}]}],[{"type":"paragraph","inlineContent":[{"type":"text","text":"- onStateChanged(backend: "},{"type":"strong","inlineContent":[{"type":"text","text":"backend"}]},{"type":"text","text":", state: ."},{"type":"strong","inlineContent":[{"type":"text","text":"loggedIn"}]},{"type":"text","text":", error:)"}]}]],[[{"type":"paragraph","inlineContent":[{"type":"text","text":"- "},{"type":"strong","inlineContent":[{"type":"text","text":"onLoginSuccessful"}]},{"type":"text","text":"(…)"}]}],[{"type":"paragraph","inlineContent":[{"type":"text","text":"- onStateChanged(backend:state: ."},{"type":"strong","inlineContent":[{"type":"text","text":"loginCompleted"}]},{"type":"text","text":", error:)"}]}]],[[{"type":"paragraph","inlineContent":[{"type":"text","text":"- "},{"type":"strong","inlineContent":[{"type":"text","text":"onLoginCancelled"}]},{"type":"text","text":"(…)"}]}],[{"type":"paragraph","inlineContent":[{"type":"text","text":"- onStateChanged(backend:state: ."},{"type":"strong","inlineContent":[{"type":"text","text":"loginAborted"}]},{"type":"text","text":", error:)"}]}]],[[{"type":"paragraph","inlineContent":[{"type":"text","text":"- "},{"type":"strong","inlineContent":[{"type":"text","text":"onLoginFailed"}]},{"type":"text","text":"(…)"}]}],[{"type":"paragraph","inlineContent":[{"type":"text","text":"- onStateChanged(backend:state: ."},{"type":"strong","inlineContent":[{"type":"text","text":"loginFailed"}]},{"type":"text","text":", error:)"}]}]],[[{"type":"paragraph","inlineContent":[{"type":"text","text":"- "},{"type":"strong","inlineContent":[{"type":"text","text":"onTokenRefreshed"}]},{"type":"text","text":"(…)"}]}],[{"type":"paragraph","inlineContent":[{"type":"text","text":"- onStateChanged(backend:state: ."},{"type":"strong","inlineContent":[{"type":"text","text":"tokenRefreshed"}]},{"type":"text","text":", error:)"}]}]],[[{"type":"paragraph","inlineContent":[{"type":"text","text":"- "},{"type":"strong","inlineContent":[{"type":"text","text":"onRefreshTokenFailed"}]},{"type":"text","text":"(…)"}]}],[{"type":"paragraph","inlineContent":[{"type":"emphasis","inlineContent":[{"type":"text","text":"no longer used, see:"}]},{"type":"text","text":" TMTickets.shared."},{"type":"strong","inlineContent":[{"type":"text","text":"validToken"}]},{"type":"text","text":"(… "},{"type":"strong","inlineContent":[{"type":"text","text":"failure"}]},{"type":"text","text":": …)"}]}]],[[{"type":"paragraph","inlineContent":[{"type":"text","text":"- "},{"type":"strong","inlineContent":[{"type":"text","text":"onRefreshTokenExpired"}]},{"type":"text","text":"(…)"}]}],[{"type":"paragraph","inlineContent":[{"type":"emphasis","inlineContent":[{"type":"text","text":"no longer used, see:"}]},{"type":"text","text":" TMTickets.shared."},{"type":"strong","inlineContent":[{"type":"text","text":"validToken"}]},{"type":"text","text":"(…)"}]}]],[[{"type":"paragraph","inlineContent":[{"type":"text","text":"- "},{"type":"strong","inlineContent":[{"type":"text","text":"onLogoutSuccessful"}]},{"type":"text","text":"(…)"}]}],[{"type":"paragraph","inlineContent":[{"type":"text","text":"- onStateChanged(backend:state: ."},{"type":"strong","inlineContent":[{"type":"text","text":"loggedOut"}]},{"type":"text","text":", error:)"}]}]],[[{"type":"paragraph","inlineContent":[{"type":"text","text":"- "},{"type":"strong","inlineContent":[{"type":"text","text":"onLogoutFailed"}]},{"type":"text","text":"(…)"}]}],[{"type":"paragraph","inlineContent":[{"type":"emphasis","inlineContent":[{"type":"text","text":"no longer used, as logout can no longer fail"}]}]}]],[[{"type":"paragraph","inlineContent":[{"type":"text","text":"- "},{"type":"strong","inlineContent":[{"type":"text","text":"onLogoutAllSuccessful"}]},{"type":"text","text":"()"}]}],[{"type":"paragraph","inlineContent":[{"type":"text","text":"- onStateChanged(backend:state: ."},{"type":"strong","inlineContent":[{"type":"text","text":"logoutCompleted"}]},{"type":"text","text":", error:)"}]}]],[[{"type":"paragraph","inlineContent":[{"type":"text","text":"- "},{"type":"strong","inlineContent":[{"type":"text","text":"onMemberUpdated"}]},{"type":"text","text":"(…)"}]}],[{"type":"paragraph","inlineContent":[{"type":"emphasis","inlineContent":[{"type":"text","text":"no longer used, see:"}]},{"type":"text","text":" TMTickets.shared."},{"type":"strong","inlineContent":[{"type":"text","text":"memberInfo"}]},{"type":"text","text":"(…)"}]}]],[[{"type":"paragraph","inlineContent":[{"type":"text","text":"- "},{"type":"strong","inlineContent":[{"type":"text","text":"onCacheCleared"}]},{"type":"text","text":"()"}]}],[{"type":"paragraph","inlineContent":[{"type":"strong","inlineContent":[{"type":"text","text":"TMTicketsOrderDelegate.didClearEventsTicketsCache"}]},{"type":"text","text":"(…)"}]}]]],"header":"row"},{"anchor":"Other-Class-Name-Changes","level":2,"type":"heading","text":"Other Class Name Changes"},{"type":"table","rows":[[[{"type":"paragraph","inlineContent":[{"type":"text","text":"Presence framework"}]}],[{"type":"paragraph","inlineContent":[{"type":"text","text":"Tickets\/Authentication frameworks"}]}]],[[{"type":"paragraph","inlineContent":[{"type":"strong","inlineContent":[{"type":"text","text":"PSDK"}]}]}],[{"type":"paragraph","inlineContent":[{"type":"strong","inlineContent":[{"type":"text","text":"TMTickets"}]}]}]],[[{"type":"paragraph","inlineContent":[{"type":"text","text":"PSDK."},{"type":"strong","inlineContent":[{"type":"text","text":"HostEnvironment"}]}]}],[{"type":"paragraph","inlineContent":[{"type":"text","text":"TMAuthentication."},{"type":"strong","inlineContent":[{"type":"text","text":"TMXDeploymentRegion"}]}]}]],[[{"type":"paragraph","inlineContent":[{"type":"text","text":"PSDK."},{"type":"strong","inlineContent":[{"type":"text","text":"SDKEnvironment"}]}]}],[{"type":"paragraph","inlineContent":[{"type":"text","text":"TMAuthentication."},{"type":"strong","inlineContent":[{"type":"text","text":"TMXDeploymentEnvironment"}]}]}]],[[{"type":"paragraph","inlineContent":[{"type":"text","text":"PSDK."},{"type":"strong","inlineContent":[{"type":"text","text":"BackendName"}]}]}],[{"type":"paragraph","inlineContent":[{"type":"text","text":"TMAuthentication."},{"type":"strong","inlineContent":[{"type":"text","text":"BackendService"}]}]}]],[[{"type":"paragraph","inlineContent":[{"type":"text","text":"PSDK."},{"type":"strong","inlineContent":[{"type":"text","text":"BrandingColors"}]}]}],[{"type":"paragraph","inlineContent":[{"type":"text","text":"TMTickets."},{"type":"strong","inlineContent":[{"type":"text","text":"BrandingColors"}]},{"type":"text","text":" or TMAuthentication."},{"type":"strong","inlineContent":[{"type":"text","text":"Branding"}]}]}]],[[{"type":"paragraph","inlineContent":[{"type":"text","text":"PSDK."},{"type":"strong","inlineContent":[{"type":"text","text":"SDKTheme"}]}]}],[{"type":"paragraph","inlineContent":[{"type":"text","text":"TMAuthentication."},{"type":"strong","inlineContent":[{"type":"text","text":"ColorTheme"}]}]}]],[[{"type":"paragraph","inlineContent":[{"type":"text","text":"PSDK."},{"type":"strong","inlineContent":[{"type":"text","text":"errorDomain"}]}]}],[{"type":"paragraph","inlineContent":[{"type":"text","text":"TMTickets."},{"type":"strong","inlineContent":[{"type":"text","text":"TicketsError.domain"}]}]}]],[[{"type":"paragraph","inlineContent":[{"type":"strong","inlineContent":[{"type":"text","text":"PresenceViewController"}]}]}],[{"type":"paragraph","inlineContent":[{"type":"strong","inlineContent":[{"type":"text","text":"TMTicketsViewController"}]}]}]],[[{"type":"paragraph","inlineContent":[{"type":"strong","inlineContent":[{"type":"text","text":"PresenceView"}]}]}],[{"type":"paragraph","inlineContent":[{"type":"strong","inlineContent":[{"type":"text","text":"TMTicketsView"}]}]}]]],"header":"row"},{"anchor":"Data-Models","level":2,"type":"heading","text":"Data Models"},{"type":"table","rows":[[[{"type":"paragraph","inlineContent":[{"type":"text","text":"Presence framework"}]}],[{"type":"paragraph","inlineContent":[{"type":"text","text":"Tickets framework"}]}]],[[{"type":"paragraph","inlineContent":[{"type":"strong","inlineContent":[{"type":"text","text":"PresenceMember"}]}]}],[{"type":"paragraph","inlineContent":[{"type":"strong","inlineContent":[{"type":"text","text":"TMMemberInfo"}]}]}]],[[{"type":"paragraph","inlineContent":[{"type":"strong","inlineContent":[{"type":"text","text":"PresenceEventOrders"}]}]}],[{"type":"paragraph","inlineContent":[{"type":"strong","inlineContent":[{"type":"text","text":"TMPurchasedEvent"}]}]}]],[[{"type":"paragraph","inlineContent":[{"type":"strong","inlineContent":[{"type":"text","text":"PresenceEvent"}]}]}],[{"type":"paragraph","inlineContent":[{"type":"strong","inlineContent":[{"type":"text","text":"TMPurchasedEventInfo"}]}]}]],[[{"type":"paragraph","inlineContent":[{"type":"strong","inlineContent":[{"type":"text","text":"PresenceOrder"}]}]}],[{"type":"paragraph","inlineContent":[{"type":"strong","inlineContent":[{"type":"text","text":"TMPurchasedOrder"}]}]}]],[[{"type":"paragraph","inlineContent":[{"type":"strong","inlineContent":[{"type":"text","text":"PresenceTicket"}]}]}],[{"type":"paragraph","inlineContent":[{"type":"strong","inlineContent":[{"type":"text","text":"TMPurchasedTicket"}]}]}]]],"header":"row"}]}],"schemaVersion":{"major":0,"minor":3,"patch":0},"sections":[],"variants":[{"paths":["\/documentation\/ticketmastertickets\/presencemigration"],"traits":[{"interfaceLanguage":"swift"}]},{"paths":["\/documentation\/ticketmastertickets\/presencemigration"],"traits":[{"interfaceLanguage":"occ"}]}],"identifier":{"url":"doc:\/\/com.ticketmaster.TicketmasterTickets\/documentation\/TicketmasterTickets\/PresenceMigration","interfaceLanguage":"swift"},"kind":"article","metadata":{"roleHeading":"Article","title":"Presence SDK Migration Guide","role":"article","modules":[{"name":"TicketmasterTickets"}]},"hierarchy":{"paths":[["doc:\/\/com.ticketmaster.TicketmasterTickets\/documentation\/TicketmasterTickets"]]},"references":{"doc://com.ticketmaster.TicketmasterTickets/documentation/TicketmasterTickets":{"role":"collection","title":"TicketmasterTickets","abstract":[{"type":"text","text":"Implementation of Ticketmaster post-purchase functionality such as viewing purchased Events, Tickets, and Barcodes."}],"identifier":"doc:\/\/com.ticketmaster.TicketmasterTickets\/documentation\/TicketmasterTickets","kind":"symbol","type":"topic","url":"\/documentation\/ticketmastertickets"}},"variantOverrides":[{"patch":[{"op":"replace","path":"\/identifier\/interfaceLanguage","value":"occ"},{"op":"add","path":"\/topicSections","value":null},{"op":"add","path":"\/seeAlsoSections","value":null}],"traits":[{"interfaceLanguage":"occ"}]}]}